glvkn_preproc/__init__.py
glvkn_preproc/glvkn_preproc.py
glvkn_preproc-0.1.0.dist-info/METADATA
glvkn_preproc-0.1.0.dist-info/WHEEL
glvkn_preproc-0.1.0.dist-info/top_level.txt
glvkn_preproc-0.1.0.dist-info/RECORD
