Metadata-Version: 2.1
Name: glvkn-preproc
Version: 0.1.0
Summary: zxczxczxc
Author: asd dasd
Requires-Python: >=3.6
Requires-Dist: nltk
Requires-Dist: spacy
Requires-Dist: pymorphy3
Requires-Dist: langedetect
Requires-Dist: tokenizer
Requires-Dist: emoji
